pymeethour/.DS_Store
pymeethour/__init__.py
pymeethour/constants/__init__.py
pymeethour/constants/constants.py
pymeethour/services/__init__.py
pymeethour/services/apiServices.py
pymeethour/type/AddContactType.py
pymeethour/type/ArchiveMeeting.py
pymeethour/type/CompletedMeetingsType.py
pymeethour/type/ContactsType.py
pymeethour/type/EditContactType.py
pymeethour/type/EditMeetingType.py
pymeethour/type/GenerateJwtType.py
pymeethour/type/LoginType.py
pymeethour/type/MissedMeeting.py
pymeethour/type/RecordingsList.py
pymeethour/type/RefreshToken.py
pymeethour/type/ScheduleMeetingType.py
pymeethour/type/UpcomingMeetings.py
pymeethour/type/ViewMeetings.py
pymeethour/type/__init__.py
pymeethour/type/time_zone.py
pymeethour/type/user_details.py
pymeethour/webhook/__init__.py
pymeethour/webhook/key.py
pymeethour/webhook/webhook_handle.py
pymeethour/webhook/webhook_payloads.py
pymeethour/webhook/webhooks.py
pymeethour/webhook/webhooksTest.py
pymeethour-1.0.2.dist-info/LICENSE
pymeethour-1.0.2.dist-info/METADATA
pymeethour-1.0.2.dist-info/WHEEL
pymeethour-1.0.2.dist-info/RECORD
