Metadata-Version: 2.1
Name: pymeethour
Version: 1.0.2
Summary: Meet Hour is video conferencing solution with End to End Encrypted and many other features such as lobby mode, Donor box & Click&Pledge Connect for fundraising, Video call recording, Youtube Live Stream etc
Home-page: https://github.com/v-empower/MeetHour-Python-SDK
Author: Meet Hour
Author-email: hello@meethour.io
Requires-Python: >=3.7,<4.0
Classifier: Programming Language :: Python :: 3
Classifier: Programming Language :: Python :: 3.7
Classifier: Programming Language :: Python :: 3.8
Classifier: Programming Language :: Python :: 3.9
Classifier: Programming Language :: Python :: 3.10
Classifier: Programming Language :: Python :: 3.11
Classifier: Programming Language :: Python :: 3.12
Requires-Dist: cryptography (>=43.0.1,<44.0.0)
Requires-Dist: requests (>=2.23.0,<3.0.0)
